ghversioner/__init__.py
ghversioner/ghversioner.py
ghversioner-0.0.2.dist-info/METADATA
ghversioner-0.0.2.dist-info/WHEEL
ghversioner-0.0.2.dist-info/licenses/LICENSE
ghversioner-0.0.2.dist-info/RECORD
